xj_comment/__init__.py
xj_comment/admin.py
xj_comment/apis.py
xj_comment/apps.py
xj_comment/models.py
xj_comment/serializers.py
xj_comment/services.py
xj_comment/tests.py
xj_comment/urls.py
xj_comment/views.py
xj_comment-1.0.4.dist-info/METADATA
xj_comment-1.0.4.dist-info/WHEEL
xj_comment-1.0.4.dist-info/top_level.txt
xj_comment-1.0.4.dist-info/RECORD
